{
  "annotations": {
    "list": [
      {
        "builtIn": 1,
        "datasource": {
          "type": "datasource",
          "uid": "grafana"
        },
        "enable": true,
        "hide": true,
        "iconColor": "rgba(0, 211, 255, 1)",
        "name": "Annotations & Alerts",
        "type": "dashboard"
      }
    ]
  },
  "editable": true,
  "fiscalYearStartMonth": 0,
  "graphTooltip": 0,
  "id": 4,
  "links": [],
  "liveNow": false,
  "panels": [
    {
      "datasource": {
        "type": "influxdb",
        "uid": "cae8dea5-a8cb-4316-9071-9eff448d4eef"
      },
      "fieldConfig": {
        "defaults": {
          "color": {
            "mode": "palette-classic"
          },
          "custom": {
            "axisBorderShow": false,
            "axisCenteredZero": false,
            "axisColorMode": "text",
            "axisLabel": "",
            "axisPlacement": "auto",
            "barAlignment": 0,
            "drawStyle": "line",
            "fillOpacity": 10,
            "gradientMode": "none",
            "hideFrom": {
              "legend": false,
              "tooltip": false,
              "viz": false
            },
            "insertNulls": false,
            "lineInterpolation": "smooth",
            "lineStyle": {
              "fill": "solid"
            },
            "lineWidth": 1,
            "pointSize": 3,
            "scaleDistribution": {
              "type": "linear"
            },
            "showPoints": "always",
            "spanNulls": true,
            "stacking": {
              "group": "A",
              "mode": "none"
            },
            "thresholdsStyle": {
              "mode": "off"
            }
          },
          "links": [],
          "mappings": [],
          "thresholds": {
            "mode": "absolute",
            "steps": [
              {
                "color": "green",
                "value": null
              },
              {
                "color": "red",
                "value": 80
              }
            ]
          },
          "unit": "binBps",
          "unitScale": true
        },
        "overrides": [
          {
            "matcher": {
              "id": "byRegexp",
              "options": "/.*Null/"
            },
            "properties": [
              {
                "id": "custom.insertNulls",
                "value": false
              },
              {
                "id": "custom.hideFrom",
                "value": {
                  "legend": true,
                  "tooltip": true,
                  "viz": true
                }
              }
            ]
          }
        ]
      },
      "gridPos": {
        "h": 11,
        "w": 23,
        "x": 0,
        "y": 0
      },
      "id": 4,
      "options": {
        "legend": {
          "calcs": [],
          "displayMode": "table",
          "placement": "right",
          "showLegend": true,
          "sortBy": "Name",
          "sortDesc": false
        },
        "tooltip": {
          "mode": "multi",
          "sort": "desc"
        }
      },
      "pluginVersion": "10.3.1",
      "targets": [
        {
          "alias": "Ingress: [[tag_source]] - [[tag_name]]",
          "datasource": {
            "type": "influxdb",
            "uid": "dc83201e-e5b0-4e39-95b5-829c265ad665"
          },
          "groupBy": [
            {
              "params": [
                "$__interval"
              ],
              "type": "time"
            },
            {
              "params": [
                "name"
              ],
              "type": "tag"
            },
            {
              "params": [
                "source"
              ],
              "type": "tag"
            },
            {
              "params": [
                "null"
              ],
              "type": "fill"
            }
          ],
          "measurement": "utilization",
          "orderByTime": "ASC",
          "policy": "default",
          "refId": "A",
          "resultFormat": "time_series",
          "select": [
            [
              {
                "params": [
                  "in_octets"
                ],
                "type": "field"
              },
              {
                "params": [],
                "type": "last"
              },
              {
                "params": [],
                "type": "difference"
              }
            ]
          ],
          "tags": [
            {
              "key": "source",
              "operator": "=~",
              "value": "/^$Devices$/"
            }
          ]
        },
        {
          "alias": "Egress: [[tag_source]] - [[tag_name]]",
          "datasource": {
            "type": "influxdb",
            "uid": "dc83201e-e5b0-4e39-95b5-829c265ad665"
          },
          "groupBy": [
            {
              "params": [
                "$__interval"
              ],
              "type": "time"
            },
            {
              "params": [
                "name"
              ],
              "type": "tag"
            },
            {
              "params": [
                "source"
              ],
              "type": "tag"
            },
            {
              "params": [
                "null"
              ],
              "type": "fill"
            }
          ],
          "measurement": "utilization",
          "orderByTime": "ASC",
          "policy": "default",
          "refId": "B",
          "resultFormat": "time_series",
          "select": [
            [
              {
                "params": [
                  "out_octets"
                ],
                "type": "field"
              },
              {
                "params": [],
                "type": "last"
              },
              {
                "params": [],
                "type": "difference"
              },
              {
                "params": [
                  " *-1"
                ],
                "type": "math"
              }
            ]
          ],
          "tags": [
            {
              "key": "source",
              "operator": "=~",
              "value": "/^$Devices$/"
            }
          ]
        }
      ],
      "title": "Ingress vs Egress",
      "type": "timeseries"
    },
    {
      "datasource": {
        "type": "influxdb",
        "uid": "cae8dea5-a8cb-4316-9071-9eff448d4eef"
      },
      "fieldConfig": {
        "defaults": {
          "color": {
            "mode": "palette-classic"
          },
          "custom": {
            "axisBorderShow": false,
            "axisCenteredZero": false,
            "axisColorMode": "text",
            "axisLabel": "",
            "axisPlacement": "auto",
            "barAlignment": 0,
            "drawStyle": "line",
            "fillOpacity": 10,
            "gradientMode": "none",
            "hideFrom": {
              "legend": false,
              "tooltip": false,
              "viz": false
            },
            "insertNulls": false,
            "lineInterpolation": "linear",
            "lineWidth": 1,
            "pointSize": 5,
            "scaleDistribution": {
              "type": "linear"
            },
            "showPoints": "never",
            "spanNulls": false,
            "stacking": {
              "group": "A",
              "mode": "none"
            },
            "thresholdsStyle": {
              "mode": "off"
            }
          },
          "links": [],
          "mappings": [],
          "thresholds": {
            "mode": "absolute",
            "steps": [
              {
                "color": "green",
                "value": null
              },
              {
                "color": "red",
                "value": 80
              }
            ]
          },
          "unit": "binBps",
          "unitScale": true
        },
        "overrides": [
          {
            "__systemRef": "hideSeriesFrom",
            "matcher": {
              "id": "byNames",
              "options": {
                "mode": "exclude",
                "names": [
                  "Ingress: XR-1 - Null0"
                ],
                "prefix": "All except:",
                "readOnly": true
              }
            },
            "properties": [
              {
                "id": "custom.hideFrom",
                "value": {
                  "legend": false,
                  "tooltip": false,
                  "viz": true
                }
              }
            ]
          }
        ]
      },
      "gridPos": {
        "h": 11,
        "w": 23,
        "x": 0,
        "y": 11
      },
      "id": 7,
      "options": {
        "legend": {
          "calcs": [],
          "displayMode": "table",
          "placement": "right",
          "showLegend": true,
          "sortBy": "Name",
          "sortDesc": true
        },
        "tooltip": {
          "mode": "multi",
          "sort": "desc"
        }
      },
      "pluginVersion": "10.3.1",
      "targets": [
        {
          "alias": "Ingress: [[tag_source]] - [[tag_name]]",
          "datasource": {
            "type": "influxdb",
            "uid": "dc83201e-e5b0-4e39-95b5-829c265ad665"
          },
          "groupBy": [
            {
              "params": [
                "$__interval"
              ],
              "type": "time"
            },
            {
              "params": [
                "name"
              ],
              "type": "tag"
            },
            {
              "params": [
                "source"
              ],
              "type": "tag"
            },
            {
              "params": [
                "null"
              ],
              "type": "fill"
            }
          ],
          "measurement": "utilization",
          "orderByTime": "ASC",
          "policy": "default",
          "refId": "A",
          "resultFormat": "time_series",
          "select": [
            [
              {
                "params": [
                  "in_octets"
                ],
                "type": "field"
              },
              {
                "params": [],
                "type": "last"
              },
              {
                "params": [
                  "1s"
                ],
                "type": "non_negative_derivative"
              }
            ]
          ],
          "tags": [
            {
              "key": "source",
              "operator": "=~",
              "value": "/^$Devices$/"
            }
          ]
        },
        {
          "alias": "Egress: [[tag_source]] - [[tag_name]]",
          "datasource": {
            "type": "influxdb",
            "uid": "dc83201e-e5b0-4e39-95b5-829c265ad665"
          },
          "groupBy": [
            {
              "params": [
                "$__interval"
              ],
              "type": "time"
            },
            {
              "params": [
                "name"
              ],
              "type": "tag"
            },
            {
              "params": [
                "source"
              ],
              "type": "tag"
            },
            {
              "params": [
                "null"
              ],
              "type": "fill"
            }
          ],
          "measurement": "utilization",
          "orderByTime": "ASC",
          "policy": "default",
          "refId": "B",
          "resultFormat": "time_series",
          "select": [
            [
              {
                "params": [
                  "out_octets"
                ],
                "type": "field"
              },
              {
                "params": [],
                "type": "last"
              },
              {
                "params": [
                  "1s"
                ],
                "type": "non_negative_derivative"
              },
              {
                "params": [
                  " *-1"
                ],
                "type": "math"
              }
            ]
          ],
          "tags": [
            {
              "key": "source",
              "operator": "=~",
              "value": "/^$Devices$/"
            }
          ]
        }
      ],
      "title": "Ingress vs Egress",
      "type": "timeseries"
    },
    {
      "datasource": {
        "type": "influxdb",
        "uid": "cae8dea5-a8cb-4316-9071-9eff448d4eef"
      },
      "fieldConfig": {
        "defaults": {
          "color": {
            "mode": "palette-classic"
          },
          "custom": {
            "axisBorderShow": false,
            "axisCenteredZero": false,
            "axisColorMode": "text",
            "axisLabel": "",
            "axisPlacement": "auto",
            "barAlignment": 0,
            "drawStyle": "line",
            "fillOpacity": 10,
            "gradientMode": "none",
            "hideFrom": {
              "legend": false,
              "tooltip": false,
              "viz": false
            },
            "insertNulls": false,
            "lineInterpolation": "linear",
            "lineWidth": 1,
            "pointSize": 5,
            "scaleDistribution": {
              "type": "linear"
            },
            "showPoints": "never",
            "spanNulls": false,
            "stacking": {
              "group": "A",
              "mode": "normal"
            },
            "thresholdsStyle": {
              "mode": "off"
            }
          },
          "links": [],
          "mappings": [],
          "thresholds": {
            "mode": "absolute",
            "steps": [
              {
                "color": "green"
              },
              {
                "color": "red",
                "value": 80
              }
            ]
          },
          "unit": "bytes",
          "unitScale": true
        },
        "overrides": [
          {
            "matcher": {
              "id": "byRegexp",
              "options": "/.*Null/"
            },
            "properties": [
              {
                "id": "custom.hideFrom",
                "value": {
                  "legend": true,
                  "tooltip": true,
                  "viz": true
                }
              }
            ]
          }
        ]
      },
      "gridPos": {
        "h": 8,
        "w": 12,
        "x": 0,
        "y": 22
      },
      "id": 2,
      "options": {
        "legend": {
          "calcs": [],
          "displayMode": "table",
          "placement": "right",
          "showLegend": true
        },
        "tooltip": {
          "mode": "multi",
          "sort": "desc"
        }
      },
      "pluginVersion": "10.3.1",
      "targets": [
        {
          "alias": "[[tag_source]] - [[tag_name]]",
          "datasource": {
            "type": "influxdb",
            "uid": "dc83201e-e5b0-4e39-95b5-829c265ad665"
          },
          "groupBy": [
            {
              "params": [
                "$__interval"
              ],
              "type": "time"
            },
            {
              "params": [
                "name"
              ],
              "type": "tag"
            },
            {
              "params": [
                "source"
              ],
              "type": "tag"
            },
            {
              "params": [
                "null"
              ],
              "type": "fill"
            }
          ],
          "measurement": "utilization",
          "orderByTime": "ASC",
          "policy": "default",
          "query": "SELECT non_negative_derivative(last(\"in_octets\"), 1s) FROM \"utilization\" WHERE (\"source\" =~ /^$Devices$/) AND $timeFilter GROUP BY time($__interval), \"name\", \"source\" fill(null)",
          "rawQuery": false,
          "refId": "A",
          "resultFormat": "time_series",
          "select": [
            [
              {
                "params": [
                  "in_octets"
                ],
                "type": "field"
              },
              {
                "params": [],
                "type": "last"
              },
              {
                "params": [
                  "1s"
                ],
                "type": "non_negative_derivative"
              }
            ]
          ],
          "tags": [
            {
              "key": "source",
              "operator": "=~",
              "value": "/^$Devices$/"
            }
          ]
        }
      ],
      "title": "Ingress",
      "type": "timeseries"
    },
    {
      "datasource": {},
      "fieldConfig": {
        "defaults": {
          "color": {
            "mode": "palette-classic"
          },
          "custom": {
            "axisBorderShow": false,
            "axisCenteredZero": false,
            "axisColorMode": "text",
            "axisLabel": "",
            "axisPlacement": "auto",
            "barAlignment": 0,
            "drawStyle": "line",
            "fillOpacity": 10,
            "gradientMode": "none",
            "hideFrom": {
              "legend": false,
              "tooltip": false,
              "viz": false
            },
            "insertNulls": false,
            "lineInterpolation": "linear",
            "lineWidth": 1,
            "pointSize": 5,
            "scaleDistribution": {
              "type": "linear"
            },
            "showPoints": "never",
            "spanNulls": true,
            "stacking": {
              "group": "A",
              "mode": "none"
            },
            "thresholdsStyle": {
              "mode": "off"
            }
          },
          "links": [],
          "mappings": [],
          "thresholds": {
            "mode": "absolute",
            "steps": [
              {
                "color": "green"
              },
              {
                "color": "red",
                "value": 80
              }
            ]
          },
          "unit": "bytes",
          "unitScale": true
        },
        "overrides": []
      },
      "gridPos": {
        "h": 8,
        "w": 12,
        "x": 12,
        "y": 22
      },
      "id": 5,
      "options": {
        "legend": {
          "calcs": [],
          "displayMode": "list",
          "placement": "bottom",
          "showLegend": true
        },
        "tooltip": {
          "mode": "single",
          "sort": "none"
        }
      },
      "pluginVersion": "8.0.6",
      "targets": [
        {
          "alias": "[[tag_source]] - [[tag_name]]",
          "datasource": {
            "type": "influxdb",
            "uid": "dc83201e-e5b0-4e39-95b5-829c265ad665"
          },
          "groupBy": [
            {
              "params": [
                "$__interval"
              ],
              "type": "time"
            },
            {
              "params": [
                "name"
              ],
              "type": "tag"
            },
            {
              "params": [
                "source"
              ],
              "type": "tag"
            },
            {
              "params": [
                "null"
              ],
              "type": "fill"
            }
          ],
          "measurement": "utilization",
          "orderByTime": "ASC",
          "policy": "default",
          "refId": "A",
          "resultFormat": "time_series",
          "select": [
            [
              {
                "params": [
                  "in_octets"
                ],
                "type": "field"
              },
              {
                "params": [],
                "type": "last"
              },
              {
                "params": [
                  "1s"
                ],
                "type": "non_negative_derivative"
              },
              {
                "params": [
                  10
                ],
                "type": "moving_average"
              }
            ]
          ],
          "tags": [
            {
              "key": "source",
              "operator": "=~",
              "value": "/^$Devices$/"
            }
          ]
        }
      ],
      "title": "Ingress Average",
      "type": "timeseries"
    },
    {
      "datasource": {},
      "fieldConfig": {
        "defaults": {
          "color": {
            "mode": "palette-classic"
          },
          "custom": {
            "axisBorderShow": false,
            "axisCenteredZero": false,
            "axisColorMode": "text",
            "axisLabel": "",
            "axisPlacement": "auto",
            "barAlignment": 0,
            "drawStyle": "line",
            "fillOpacity": 10,
            "gradientMode": "none",
            "hideFrom": {
              "legend": false,
              "tooltip": false,
              "viz": false
            },
            "insertNulls": false,
            "lineInterpolation": "linear",
            "lineWidth": 1,
            "pointSize": 5,
            "scaleDistribution": {
              "type": "linear"
            },
            "showPoints": "never",
            "spanNulls": false,
            "stacking": {
              "group": "A",
              "mode": "none"
            },
            "thresholdsStyle": {
              "mode": "off"
            }
          },
          "fieldMinMax": true,
          "links": [],
          "mappings": [],
          "thresholds": {
            "mode": "absolute",
            "steps": [
              {
                "color": "green"
              },
              {
                "color": "red",
                "value": 80
              }
            ]
          },
          "unit": "decbytes",
          "unitScale": true
        },
        "overrides": [
          {
            "__systemRef": "hideSeriesFrom",
            "matcher": {
              "id": "byNames",
              "options": {
                "mode": "exclude",
                "names": [
                  "SITE-A - GigabitEthernet0/0/0/0"
                ],
                "prefix": "All except:",
                "readOnly": true
              }
            },
            "properties": [
              {
                "id": "custom.hideFrom",
                "value": {
                  "legend": false,
                  "tooltip": false,
                  "viz": true
                }
              }
            ]
          }
        ]
      },
      "gridPos": {
        "h": 8,
        "w": 12,
        "x": 0,
        "y": 30
      },
      "id": 3,
      "options": {
        "legend": {
          "calcs": [],
          "displayMode": "list",
          "placement": "bottom",
          "showLegend": true
        },
        "tooltip": {
          "mode": "multi",
          "sort": "desc"
        }
      },
      "pluginVersion": "10.3.1",
      "targets": [
        {
          "alias": "[[tag_source]] - [[tag_name]]",
          "datasource": {
            "type": "influxdb",
            "uid": "dc83201e-e5b0-4e39-95b5-829c265ad665"
          },
          "groupBy": [
            {
              "params": [
                "$__interval"
              ],
              "type": "time"
            },
            {
              "params": [
                "name"
              ],
              "type": "tag"
            },
            {
              "params": [
                "source"
              ],
              "type": "tag"
            },
            {
              "params": [
                "null"
              ],
              "type": "fill"
            }
          ],
          "measurement": "utilization",
          "orderByTime": "ASC",
          "policy": "default",
          "refId": "A",
          "resultFormat": "time_series",
          "select": [
            [
              {
                "params": [
                  "out_octets"
                ],
                "type": "field"
              },
              {
                "params": [],
                "type": "last"
              },
              {
                "params": [
                  "1s"
                ],
                "type": "non_negative_derivative"
              }
            ]
          ],
          "tags": [
            {
              "key": "source",
              "operator": "=~",
              "value": "/^$Devices$/"
            }
          ]
        }
      ],
      "title": "Egress",
      "type": "timeseries"
    },
    {
      "datasource": {},
      "fieldConfig": {
        "defaults": {
          "color": {
            "mode": "palette-classic"
          },
          "custom": {
            "axisBorderShow": false,
            "axisCenteredZero": false,
            "axisColorMode": "text",
            "axisLabel": "",
            "axisPlacement": "auto",
            "barAlignment": 0,
            "drawStyle": "line",
            "fillOpacity": 10,
            "gradientMode": "none",
            "hideFrom": {
              "legend": false,
              "tooltip": false,
              "viz": false
            },
            "insertNulls": false,
            "lineInterpolation": "linear",
            "lineWidth": 1,
            "pointSize": 5,
            "scaleDistribution": {
              "type": "linear"
            },
            "showPoints": "never",
            "spanNulls": true,
            "stacking": {
              "group": "A",
              "mode": "none"
            },
            "thresholdsStyle": {
              "mode": "off"
            }
          },
          "links": [],
          "mappings": [],
          "thresholds": {
            "mode": "absolute",
            "steps": [
              {
                "color": "green"
              },
              {
                "color": "red",
                "value": 80
              }
            ]
          },
          "unit": "Bps",
          "unitScale": true
        },
        "overrides": []
      },
      "gridPos": {
        "h": 8,
        "w": 12,
        "x": 12,
        "y": 30
      },
      "id": 6,
      "options": {
        "legend": {
          "calcs": [],
          "displayMode": "list",
          "placement": "bottom",
          "showLegend": true
        },
        "tooltip": {
          "mode": "single",
          "sort": "none"
        }
      },
      "pluginVersion": "8.0.6",
      "targets": [
        {
          "alias": "[[tag_source]] - [[tag_name]]",
          "datasource": {
            "type": "influxdb",
            "uid": "dc83201e-e5b0-4e39-95b5-829c265ad665"
          },
          "groupBy": [
            {
              "params": [
                "$__interval"
              ],
              "type": "time"
            },
            {
              "params": [
                "name"
              ],
              "type": "tag"
            },
            {
              "params": [
                "source"
              ],
              "type": "tag"
            },
            {
              "params": [
                "null"
              ],
              "type": "fill"
            }
          ],
          "measurement": "utilization",
          "orderByTime": "ASC",
          "policy": "default",
          "refId": "A",
          "resultFormat": "time_series",
          "select": [
            [
              {
                "params": [
                  "out_octets"
                ],
                "type": "field"
              },
              {
                "params": [],
                "type": "last"
              },
              {
                "params": [
                  "1s"
                ],
                "type": "non_negative_derivative"
              },
              {
                "params": [
                  10
                ],
                "type": "moving_average"
              }
            ]
          ],
          "tags": [
            {
              "key": "source",
              "operator": "=~",
              "value": "/^$Devices$/"
            }
          ]
        }
      ],
      "title": "Egress Average",
      "type": "timeseries"
    }
  ],
  "refresh": "5s",
  "schemaVersion": 39,
  "tags": [],
  "templating": {
    "list": [
      {
        "current": {
          "selected": true,
          "text": [
            "All"
          ],
          "value": [
            "$__all"
          ]
        },
        "datasource": {
          "type": "influxdb",
          "uid": "cae8dea5-a8cb-4316-9071-9eff448d4eef"
        },
        "definition": "SHOW TAG VALUES WITH KEY=\"source\"",
        "hide": 0,
        "includeAll": true,
        "multi": true,
        "name": "Devices",
        "options": [],
        "query": "SHOW TAG VALUES WITH KEY=\"source\"",
        "refresh": 1,
        "regex": "",
        "skipUrlSync": false,
        "sort": 1,
        "tagValuesQuery": "",
        "tagsQuery": "",
        "type": "query",
        "useTags": false
      }
    ]
  },
  "time": {
    "from": "now-30s",
    "to": "now"
  },
  "timepicker": {
    "refresh_intervals": [
      "5s",
      "10s",
      "30s",
      "1m",
      "5m",
      "15m",
      "30m",
      "1h",
      "2h",
      "1d"
    ]
  },
  "timezone": "",
  "title": "Topology Traffic",
  "uid": "b5b4ce9f-23e1-4ff2-9065-0d34a82a3eb9",
  "version": 2,
  "weekStart": ""
}